{"data":{"_id":5000,"properties":{"id":{"name":"id","kind":"scalar","primary":true,"type":"number","array":false,"runtimeType":"number"},"name":{"name":"name","kind":"scalar","getter":false,"setter":false,"type":"string","array":false,"runtimeType":"string"},"token":{"name":"token","kind":"scalar","getter":false,"setter":false,"type":"string","array":false,"runtimeType":"string"},"fcmToken":{"name":"fcmToken","kind":"scalar","nullable":true,"getter":false,"setter":false,"fieldNames":["fcm_token"],"type":"string","array":false,"runtimeType":"string"},"abilities":{"name":"abilities","kind":"scalar","type":"text","nullable":true,"getter":false,"setter":false,"array":false,"runtimeType":"string"},"expiresAt":{"name":"expiresAt","kind":"scalar","type":"datetime","nullable":true,"getter":false,"setter":false,"fieldNames":["expires_at"],"array":false,"runtimeType":"Date"},"createdAt":{"name":"createdAt","kind":"scalar","type":"datetime","getter":false,"setter":false,"fieldNames":["created_at"],"array":false,"runtimeType":"Date"},"updatedAt":{"name":"updatedAt","kind":"scalar","type":"datetime","getter":false,"setter":false,"fieldNames":["updated_at"],"array":false,"runtimeType":"Date"},"user":{"name":"user","kind":"m:1","cascade":["persist"],"owner":true,"type":"UsersEntity","array":false,"runtimeType":"{ id: number; } & import\"/Users/yakanta/dev/node-project/nest-booking-ticket/node_modules/@mikro-orm/core/index\".Reference<UsersEntity & object>","ref":true}},"primaryKeys":["id"],"filters":{},"hooks":{},"indexes":[],"uniques":[],"className":"AccessTokensEntity","path":"./src/entities/access-tokens.entity.ts","collection":"access_tokens","name":"AccessTokensEntity","abstract":false,"internal":true,"constructorParams":[],"toJsonParams":[],"useCache":true,"compositePK":false,"simplePK":true},"origin":"./src/entities/access-tokens.entity.ts","hash":"bdab366cdef6a88b2b86d02ce701fb7d","version":"6.4.0"}
